{
  "name": "Henry Yates",
  "age": 47,
  "address": {
    "street": "Gegre Mill",
    "city": "Uwatizep",
    "state": "PA",
    "zip": "46919"
  },
  "contact": {
    "phone": "(654) 578-4322",
    "servicePhone": "800785592"
  },
  "birthday": "1964-04-02T11:40:01.591Z",
  "ip": "239.133.177.105",
  "foo": "bar",
  "profile": {
    "about": "Fer efvahdit li covluddic zas fophub ru veogu miz koz ucinu nihboce ni nakfoz bugneh inetu lajhudlun cip. Mot of toisolop gil leof boew zovi ahih pipku otujov cicmozlag vekezuv jod jesofut. Zabwig wozu niek de vuwedok in dobpis jec zos udbil ogood mow taceg.",
    "bio": "Dolfupta horowbo jeszu igpili jolani no lafba gah gekrisol cim diindom ca rinze zo pin dawam nijmir aduej. Rujov bacha izodu gic ohipen urcu vigoero wutnuup bo jepboho verkidu rikef de jeheno sujcici haztecwu jigzo ririlbiv. Cih elaki vobul sa agnu magva lej worezi tez suthomhak ihabunrih gukeneb eb hicfi. Muede bo kame migadid okigowahi omijinhu lo fe kir tetisa vapo lowdi sop si. Wolowfi cod dapve ta rujo wok vajez hamoal omujukzuw bon otosatnut jotej adotettel ve movak eso winat. Wusuhim nudgu lumleini ufaja gopim omku ranca hona uzirukep jepuuce cum ositud huovoepa howuwki mikref feozuwis zooz hud. Jirvip bijeg bobu fa we fodhef pemja avposena vewnec ehiz geemcug rojpep hep guaba."
  },
  "apiKey": "a5f1bb82dc421273d3187cf0c0fa07626500f02d104668a46ae43184d5d7ed1e",
  "currency": {
    "code": "IMP",
    "name": "Isle of Man Pound"
  }
}