{
  "name": "Robert Walker",
  "age": 63,
  "address": {
    "street": "Juuw Boulevard",
    "city": "Wojinfe",
    "state": "DE",
    "zip": "35439"
  },
  "contact": {
    "phone": "(475) 632-7504",
    "servicePhone": "800215756"
  },
  "birthday": "1983-12-03T08:02:23.045Z",
  "ip": "138.25.105.127",
  "foo": "bar",
  "profile": {
    "about": "Hikmuhdo vikatwu seto uctow ap uhawa ig piworad juw tocuw bu etemi lettogada tepavzow wofop. On edpanpu datgacet ujod kiplam nupizoke dujav rapama ferveguk rinas tiv jalvadbe zuaflik ja ol agome hu. Kuk jivibar caizdef alerusig ulgu silemzak hi zalcog fa obekukah mir kikupin porepad anilo arjigat ro nal cifivke. Geb sazo fuhmeghu ipigogsu gerdo him sewruoki hap sa gafo on caghuzac ibuuz rupbawtah.",
    "bio": "Sogis la ni ur mersehbiz sifdoksav kuaw havo fij nethos luloum huf. Azebol wo mewul veugmop redbobani ja zi wetjodu kapko evu pufeig egagatku. Ceaswus daw rocjutif ewom etava kopat dod pa seri katrig gulgan ba ogsigcu daameas za zozke ib."
  },
  "apiKey": "10140d7b96100ea27ffb62e866a64f2396b1d28211b7e6eee4acd1ae7f535d45",
  "currency": {
    "code": "NZD",
    "name": "New Zealand Dollar"
  }
}